letta/__init__.py
letta/agent.py
letta/config.py
letta/constants.py
letta/database_utils.py
letta/errors.py
letta/interface.py
letta/log.py
letta/log_context.py
letta/main.py
letta/memory.py
letta/pytest.ini
letta/settings.py
letta/streaming_interface.py
letta/streaming_utils.py
letta/system.py
letta/utils.py
letta/validators.py
letta/adapters/letta_llm_adapter.py
letta/adapters/letta_llm_request_adapter.py
letta/adapters/letta_llm_stream_adapter.py
letta/adapters/simple_llm_request_adapter.py
letta/adapters/simple_llm_stream_adapter.py
letta/agents/__init__.py
letta/agents/agent_loop.py
letta/agents/base_agent.py
letta/agents/base_agent_v2.py
letta/agents/ephemeral_agent.py
letta/agents/ephemeral_summary_agent.py
letta/agents/exceptions.py
letta/agents/helpers.py
letta/agents/letta_agent.py
letta/agents/letta_agent_batch.py
letta/agents/letta_agent_v2.py
letta/agents/letta_agent_v3.py
letta/agents/voice_agent.py
letta/agents/voice_sleeptime_agent.py
letta/cli/cli.py
letta/cli/cli_load.py
letta/client/__init__.py
letta/client/streaming.py
letta/client/utils.py
letta/data_sources/__init__.py
letta/data_sources/connectors.py
letta/data_sources/connectors_helper.py
letta/data_sources/redis_client.py
letta/exceptions/logging.py
letta/functions/__init__.py
letta/functions/ast_parsers.py
letta/functions/async_composio_toolset.py
letta/functions/composio_helpers.py
letta/functions/functions.py
letta/functions/helpers.py
letta/functions/interface.py
letta/functions/prompts.py
letta/functions/schema_generator.py
letta/functions/schema_validator.py
letta/functions/types.py
letta/functions/typescript_parser.py
letta/functions/function_sets/base.py
letta/functions/function_sets/builtin.py
letta/functions/function_sets/files.py
letta/functions/function_sets/multi_agent.py
letta/functions/function_sets/voice.py
letta/functions/mcp_client/exceptions.py
letta/functions/mcp_client/types.py
letta/groups/dynamic_multi_agent.py
letta/groups/helpers.py
letta-0.16.4.dist-info/METADATA
letta-0.16.4.dist-info/WHEEL
letta-0.16.4.dist-info/entry_points.txt
letta-0.16.4.dist-info/licenses/LICENSE
letta-0.16.4.dist-info/RECORD
